odoo/addons/account_invoice_line_description/README.rst
odoo/addons/account_invoice_line_description/__init__.py
odoo/addons/account_invoice_line_description/__manifest__.py
odoo/addons/account_invoice_line_description/i18n/account_invoice_line_description.pot
odoo/addons/account_invoice_line_description/i18n/ar.po
odoo/addons/account_invoice_line_description/i18n/bs.po
odoo/addons/account_invoice_line_description/i18n/ca.po
odoo/addons/account_invoice_line_description/i18n/cs.po
odoo/addons/account_invoice_line_description/i18n/de.po
odoo/addons/account_invoice_line_description/i18n/en_GB.po
odoo/addons/account_invoice_line_description/i18n/es.po
odoo/addons/account_invoice_line_description/i18n/es_CR.po
odoo/addons/account_invoice_line_description/i18n/es_EC.po
odoo/addons/account_invoice_line_description/i18n/es_ES.po
odoo/addons/account_invoice_line_description/i18n/es_MX.po
odoo/addons/account_invoice_line_description/i18n/et.po
odoo/addons/account_invoice_line_description/i18n/fr.po
odoo/addons/account_invoice_line_description/i18n/fr_CH.po
odoo/addons/account_invoice_line_description/i18n/hr.po
odoo/addons/account_invoice_line_description/i18n/hr_HR.po
odoo/addons/account_invoice_line_description/i18n/hu.po
odoo/addons/account_invoice_line_description/i18n/it.po
odoo/addons/account_invoice_line_description/i18n/ja.po
odoo/addons/account_invoice_line_description/i18n/lt.po
odoo/addons/account_invoice_line_description/i18n/mk.po
odoo/addons/account_invoice_line_description/i18n/mn.po
odoo/addons/account_invoice_line_description/i18n/nb.po
odoo/addons/account_invoice_line_description/i18n/nl.po
odoo/addons/account_invoice_line_description/i18n/nl_BE.po
odoo/addons/account_invoice_line_description/i18n/nl_NL.po
odoo/addons/account_invoice_line_description/i18n/pt.po
odoo/addons/account_invoice_line_description/i18n/pt_BR.po
odoo/addons/account_invoice_line_description/i18n/pt_PT.po
odoo/addons/account_invoice_line_description/i18n/ro.po
odoo14_addon_account_invoice_line_description-14.0.1.0.1.dist-info/METADATA
odoo14_addon_account_invoice_line_description-14.0.1.0.1.dist-info/WHEEL
odoo14_addon_account_invoice_line_description-14.0.1.0.1.dist-info/top_level.txt
odoo14_addon_account_invoice_line_description-14.0.1.0.1.dist-info/RECORD
